sca_rhythm/__init__.py
sca_rhythm/progress.py
sca_rhythm-0.6.15.dist-info/LICENSE.md
sca_rhythm-0.6.15.dist-info/METADATA
sca_rhythm-0.6.15.dist-info/WHEEL
sca_rhythm-0.6.15.dist-info/RECORD
