Metadata-Version: 2.1
Name: sca_rhythm
Version: 0.6.15
Summary: Create and manage workflows using Celery tasks
Author: Deepak Duggirala
Author-email: deepakduggi@gmail.com
Requires-Python: >=3.10,<4.0
Classifier: Programming Language :: Python :: 3
Classifier: Programming Language :: Python :: 3.10
Classifier: Programming Language :: Python :: 3.11
Classifier: Programming Language :: Python :: 3.12
Requires-Dist: celery (>=5.2.7,<5.3.0)
Requires-Dist: pymongo (>=4.5.0,<5.0.0)
